Metadata-Version: 1.1
Name: taiga-contrib-slack-auth
Version: 1.0.1
Summary: The Taiga plugin for slack authentication
Home-page: https://github.com/sjaakiejj/taiga-contrib-slack-auth
Author: Jacobus Meulen
Author-email: jacobus@openbusiness.com.sg
License: AGPL
Keywords: taiga,slack,auth,plugin
Platform: UNKNOWN
Classifier: Programming Language :: Python
Classifier: Development Status :: 4 - Beta
Classifier: Framework :: Django
Classifier: Intended Audience :: Developers
Classifier: License :: OSI Approved :: GNU Affero General Public License v3
Classifier: Operating System :: OS Independent
Classifier: Programming Language :: Python
Classifier: Topic :: Internet :: WWW/HTTP
